faceblur/__init__.py
faceblur/app.py
faceblur/box.py
faceblur/exception.py
faceblur/help.py
faceblur/image.py
faceblur/path.py
faceblur/progress.py
faceblur/threading.py
faceblur/av/__init__.py
faceblur/av/container.py
faceblur/av/filter.py
faceblur/av/frame.py
faceblur/av/packet.py
faceblur/av/stream.py
faceblur/av/video.py
faceblur/faces/__init__.py
faceblur/faces/debug.py
faceblur/faces/detector.py
faceblur/faces/dlib.py
faceblur/faces/identify.py
faceblur/faces/interpolate.py
faceblur/faces/mediapipe.py
faceblur/faces/mode.py
faceblur/faces/model.py
faceblur/faces/obfuscate.py
faceblur/faces/process.py
faceblur/faces/track.py
faceblur/frontend/__init__.py
faceblur/frontend/cli.py
faceblur/frontend/wx.py
faceblur-1.2.0.dist-info/licenses/LICENSE
faceblur-1.2.0.dist-info/METADATA
faceblur-1.2.0.dist-info/WHEEL
faceblur-1.2.0.dist-info/entry_points.txt
faceblur-1.2.0.dist-info/top_level.txt
faceblur-1.2.0.dist-info/RECORD
