Metadata-Version: 2.4
Name: faceblur
Version: 1.2.0
Summary: Faceblur is a Python library and command-line tool to obfuscate faces from photos and videos via blurring them.
Author-email: Simona Dimitrova <nimeria1308@gmail.com>
License: BSD 3-Clause License
Project-URL: Homepage, https://github.com/nimeria1308/faceblur
Keywords: faceblur,deidentify,obfuscate,anonymize,face,recognition,video,image
Classifier: License :: OSI Approved :: BSD License
Classifier: Programming Language :: Python
Classifier: Programming Language :: Python :: 3
Classifier: Intended Audience :: Science/Research
Classifier: Topic :: Desktop Environment
Classifier: Topic :: Multimedia :: Video :: Display
Classifier: Topic :: Scientific/Engineering :: Image Processing
Requires-Python: >=3.12
License-File: LICENSE
Requires-Dist: av==14.2.0
Requires-Dist: pymediainfo>=6.1.0
Requires-Dist: mediapipe>=0.10.20
Requires-Dist: face-recognition>=1.3.0
Requires-Dist: setuptools>=75.8.0
Requires-Dist: pillow>=11.1.0
Requires-Dist: pillow_heif>=0.21.0
Requires-Dist: tqdm>=4.67.1
Requires-Dist: wxPython>=4.2.2
Provides-Extra: dev
Requires-Dist: autopep8; extra == "dev"
Requires-Dist: pytest; extra == "dev"
Dynamic: license-file
